{"data":{"allUserCountsJson":{"totalCount":1,"edges":[{"node":{"nameWithOwner":"KhronosGroup/MoltenVK","forkCount":112,"primaryLanguage":"Objective-C++","license":"Apache-2.0","description":"MoltenVK is an implementation of the high-performance, industry-standard Vulkan graphics and compute API, that runs on Apple's Metal graphics framework, bringing Vulkan to iOS and macOS.","detectedLanguage":"en","stargazersCount":1463,"watchersCount":109,"rolloCountStars":9,"rolloCountContribs":1,"contribsProrata":0.004524886877828055,"starsProrata":0.006151742993848257}}]},"whole":{"edges":[{"node":{"primaryLanguage":"Objective-C++","license":"Apache-2.0"}},{"node":{"primaryLanguage":"Objective-C++","license":null}}]}},"pageContext":{"order":"contribsProrata","primaryLanguage":"Objective-C++"}}